LICENSE
MANIFEST.in
README.md
hiveary-agent
hiveary.conf.example
setup.py
arch/hiveary-agent.service
hiveary/__init__.py
hiveary/ca-bundle.pem
hiveary/controller.py
hiveary/daemon.py
hiveary/network.py
hiveary/oauth_client.py
hiveary/paths.py
hiveary/info/__init__.py
hiveary/info/dmesg.py
hiveary/info/logs.py
hiveary/info/system.py
hiveary/info/wincom.py
hiveary/monitors/__init__.py
hiveary_agent.egg-info/PKG-INFO
hiveary_agent.egg-info/SOURCES.txt
hiveary_agent.egg-info/dependency_links.txt
hiveary_agent.egg-info/requires.txt
hiveary_agent.egg-info/top_level.txt
initd/hiveary-agent
monitors/processes.py
monitors/resources.py
monitors/systemd_service_status.py
monitors/sysv_service_status.py
monitors/windows_service_status.py