Metadata-Version: 1.0
Name: hiveary-agent
Version: 1.4.0
Summary: Hiveary Monitoring Agent
Home-page: http://hiveary.com
Author: Hiveary
Author-email: info@hiveary.com
License: Simplified BSD
Platform: UNKNOWN
